gprinter/__init__.py
gprinter/core.py
inventree_gprinter_plugin-0.1.3.dist-info/LICENSE
inventree_gprinter_plugin-0.1.3.dist-info/METADATA
inventree_gprinter_plugin-0.1.3.dist-info/WHEEL
inventree_gprinter_plugin-0.1.3.dist-info/entry_points.txt
inventree_gprinter_plugin-0.1.3.dist-info/top_level.txt
inventree_gprinter_plugin-0.1.3.dist-info/RECORD
