Metadata-Version: 2.1
Name: inventree-gprinter-plugin
Version: 0.1.3
Summary: Gprinter label printer plugin for InvenTree
Author: Daqi Song
Author-email: dqaria@gmail.com
License: MIT
Requires-Python: >=3.9
License-File: LICENSE
Requires-Dist: pyusb
